qddate/__init__.py
qddate/dirty.py
qddate/qdparser.py
qddate/patterns/__init__.py
qddate/patterns/base.py
qddate/patterns/bg.py
qddate/patterns/cz.py
qddate/patterns/de.py
qddate/patterns/es.py
qddate/patterns/fr.py
qddate/patterns/it.py
qddate/patterns/pt.py
qddate/patterns/ru.py
qddate-0.1.1.dist-info/DESCRIPTION.rst
qddate-0.1.1.dist-info/METADATA
qddate-0.1.1.dist-info/RECORD
qddate-0.1.1.dist-info/WHEEL
qddate-0.1.1.dist-info/metadata.json
qddate-0.1.1.dist-info/top_level.txt
