Metadata-Version: 2.0
Name: qddate
Version: 0.1.1
Summary: Quick and dirty date parsing Python library to parse HTML dates really fast
Home-page: https://github.com/ivbeg/qddate
Author: Ivan Begtin
Author-email: ivan@begtin.tech
License: BSD
Keywords: date datetime
Platform: UNKNOWN
Classifier: Development Status :: 2 - Pre-Alpha
Classifier: Intended Audience :: Developers
Classifier: License :: OSI Approved :: BSD License
Classifier: Natural Language :: English
Classifier: Programming Language :: Python :: 3
Classifier: Programming Language :: Python :: 3.3
Classifier: Programming Language :: Python :: 3.4
Classifier: Programming Language :: Python :: 3.5
Classifier: Programming Language :: Python :: 3.6
Classifier: Programming Language :: Python :: Implementation :: CPython
Classifier: Programming Language :: Python :: Implementation :: PyPy
Requires-Dist: pyparsing
